aiosqlite/__init__.py
aiosqlite/__version__.py
aiosqlite/context.py
aiosqlite/core.py
aiosqlite/cursor.py
aiosqlite/py.typed
aiosqlite/tests/__init__.py
aiosqlite/tests/__main__.py
aiosqlite/tests/helpers.py
aiosqlite/tests/perf.py
aiosqlite/tests/smoke.py
aiosqlite-0.16.1.dist-info/LICENSE
aiosqlite-0.16.1.dist-info/WHEEL
aiosqlite-0.16.1.dist-info/METADATA
aiosqlite-0.16.1.dist-info/RECORD
